mypackage/__init__.py
mypackage/github.py
mypackage/main.py
stegano_pro-0.0.1.dist-info/LICENSE
stegano_pro-0.0.1.dist-info/METADATA
stegano_pro-0.0.1.dist-info/WHEEL
stegano_pro-0.0.1.dist-info/top_level.txt
stegano_pro-0.0.1.dist-info/RECORD
