Metadata-Version: 2.1
Name: stegano-pro
Version: 0.0.1
Summary: test package for documentation
Home-page: https://github.com/ZakariaHibaoui/lp2e
Author: ZHibaoui
Author-email: HelloMe@proton.me
Project-URL: Bug Tracker, https://github.com/ZakariaHibaoui/lp2e/issues
Classifier: Programming Language :: Python :: 3
Classifier: License :: OSI Approved :: MIT License
Classifier: Operating System :: OS Independent
Requires-Python: >=3.6
License-File: LICENSE
